phrugal/__init__.py
phrugal/_version.py
phrugal/cli.py
phrugal/composer.py
phrugal/composition.py
phrugal/decorated_image.py
phrugal/decoration_config.py
phrugal/exif.py
phrugal/geocode.py
phrugal/image.py
phrugal/types.py
phrugal-0.0.3rc4.dist-info/licenses/LICENSE
phrugal-0.0.3rc4.dist-info/METADATA
phrugal-0.0.3rc4.dist-info/WHEEL
phrugal-0.0.3rc4.dist-info/entry_points.txt
phrugal-0.0.3rc4.dist-info/top_level.txt
phrugal-0.0.3rc4.dist-info/RECORD
