Metadata-Version: 2.4
Name: phrugal
Version: 0.0.3rc4
Summary: A tool for efficient multi-image printing with borders
Author-email: Martin Demling <0x6d64@martin-demling.de>
License: GPL-3.0-or-later
Classifier: Programming Language :: Python :: 3.7
Classifier: Operating System :: OS Independent
Requires-Python: >=3.7
License-File: LICENSE
Requires-Dist: Pillow>=8.0.0
Requires-Dist: exifread>=3.0
Requires-Dist: geopy>=2.4.1
Provides-Extra: dev
Requires-Dist: black; extra == "dev"
Requires-Dist: ruff; extra == "dev"
Requires-Dist: coverage; extra == "dev"
Dynamic: license-file
